[
    {
        "type": "input",
        "request_description": "Field to enter the first name",
        "identifier_type": "XPath",
        "identifier_tracking": "/html/body/div/form/input[@placeholder='Nome']",
        "naming": "input_first_name",
        "error": false
    },
    {
        "type": "input",
        "request_description": "Field to enter the last name",
        "identifier_type": "XPath",
        "identifier_tracking": "/html/body/div/form/input[@placeholder='Sobrenome']",
        "naming": "input_last_name",
        "error": false
    },
    {
        "type": "input",
        "request_description": "Field to enter the email",
        "identifier_type": "XPath",
        "identifier_tracking": "/html/body/div/form/input[@placeholder='E-mail']",
        "naming": "input_email",
        "error": false
    },
    {
        "type": "input",
        "request_description": "Field to confirm the email",
        "identifier_type": "XPath",
        "identifier_tracking": "/html/body/div/form/input[@placeholder='Confirmar e-mail']",
        "naming": "input_confirm_email",
        "error": false
    },
    {
        "type": "input",
        "request_description": "Field to enter the password",
        "identifier_type": "XPath",
        "identifier_tracking": "/html/body/div/form/input[@placeholder='Senha']",
        "naming": "input_password",
        "error": false
    },
    {
        "type": "input",
        "request_description": "Field to confirm the password",
        "identifier_type": "XPath",
        "identifier_tracking": "/html/body/div/form/input[@placeholder='Confirmar senha']",
        "naming": "input_confirm_password",
        "error": false
    },
    {
        "type": "button",
        "request_description": "Button to submit the sign up form",
        "identifier_type": "XPath",
        "identifier_tracking": "/html/body/div/form/img[@src='src/assets/sign_up_button.svg']",
        "naming": "button_sign_up",
        "error": false
    },
    {
        "type": "checkbox",
        "request_description": "Checkbox to agree with the terms of use",
        "identifier_type": "XPath",
        "identifier_tracking": "/html/body/div/form/img[@src='src/assets/ball_icon.svg']",
        "naming": "checkbox_terms_of_use",
        "error": false
    }
]