{
  "testCase": "Login User with incorrect email and password",
  "modules": [
    {
      "url": "http://automationexercise.com",
      "purpose": "Home page of the application",
      "execution_steps": [
        {
          "step": "Launch browser",
          "extracted_data": []
        },
        {
          "step": "Navigate to url 'http://automationexercise.com'",
          "extracted_data": []
        },
        {
          "step": "Verify that home page is visible successfully",
          "extracted_data": []
        },
        {
          "step": "Click on 'Signup / Login' button",
          "extracted_data": []
        }
      ]
    },
    {
      "url": "https://automationexercise.com/login",
      "purpose": "Login page for users to enter their credentials",
      "execution_steps": [
        {
          "step": "Verify 'Login to your account' is visible",
          "extracted_data": []
        },
        {
          "step": "Enter incorrect email address and password",
          "extracted_data": []
        },
        {
          "step": "Click 'login' button",
          "extracted_data": []
        },
        {
          "step": "Verify error 'Your email or password is incorrect!' is visible",
          "extracted_data": []
        }
      ]
    }
  ]
}

